yahoo_parser/__about__.py
yahoo_parser/__init__.py
yahoo_parser-6.0.0.dist-info/METADATA
yahoo_parser-6.0.0.dist-info/WHEEL
yahoo_parser-6.0.0.dist-info/licenses/LICENSE.txt
yahoo_parser-6.0.0.dist-info/RECORD
